{  
    "channel": 1,  
    "notes": {    
        "move_forward": 20,   
        "move_backward": 21,    
        "strafe_left": 22,    
        "strafe_right": 23,    
        "rotate_left": 24,    
        "rotate_right": 25,    
        "speaker_up": 26,    
        "speaker_down": 27
    },  
    "controlchange": {    
        "move_speed": 30,    
        "rotate_speed": 31,    
        "speaker_speed": 32,     
        "speaker_position_q1": 33,     
        "speaker_position_q2": 34,     
        "speaker_position_q3": 35,     
        "speaker_position_q4": 36,    
        "speaker_position_reset": 37 
    },
    "resend": 0
}